dodonacli/__init__.py
dodonacli/main.py
dodonacli/commands/__init__.py
dodonacli/commands/cli_next.py
dodonacli/commands/display.py
dodonacli/commands/info.py
dodonacli/commands/post.py
dodonacli/commands/select.py
dodonacli/commands/settings.py
dodonacli/commands/status.py
dodonacli/commands/submission.py
dodonacli/commands/tutorial.py
dodonacli/commands/up.py
dodonacli/source/__init__.py
dodonacli/source/get_data.py
dodonacli/source/interactive_tutorial.py
dodonacli/source/pretty_console.py
dodonacli/source/pretty_print.py
dodonacli/source/pretty_printer.py
dodonacli/source/set_data.py
dodonacli/source/submission_data_handler.py
dodonacli/source/syntax_checker.py
DodonaCLI-2025.1.26.dist-info/LICENSE
DodonaCLI-2025.1.26.dist-info/METADATA
DodonaCLI-2025.1.26.dist-info/WHEEL
DodonaCLI-2025.1.26.dist-info/entry_points.txt
DodonaCLI-2025.1.26.dist-info/top_level.txt
DodonaCLI-2025.1.26.dist-info/RECORD
