Metadata-Version: 2.2
Name: DodonaCLI
Version: 2025.1.26
Summary: A CLI tool for Dodona
Author-email: Bram Windey <windey.bram@gmail.com>
License: MIT License
Project-URL: Homepage, https://github.com/BWindey/DodonaCLI
Keywords: dodona,cli
Classifier: License :: OSI Approved :: MIT License
Classifier: Programming Language :: Python
Classifier: Programming Language :: Python :: 3
Requires-Python: >=3.8
License-File: LICENSE
Requires-Dist: bs4
Requires-Dist: click
Requires-Dist: click-default-group
Requires-Dist: markdownify
Requires-Dist: packaging
Requires-Dist: pkg-info
Requires-Dist: rich
